lightning_hivemind/__about__.py
lightning_hivemind/__init__.py
lightning_hivemind/strategy.py
lightning_Hivemind-0.1.0.dist-info/LICENSE
lightning_Hivemind-0.1.0.dist-info/METADATA
lightning_Hivemind-0.1.0.dist-info/WHEEL
lightning_Hivemind-0.1.0.dist-info/top_level.txt
lightning_Hivemind-0.1.0.dist-info/RECORD
