Metadata-Version: 2.1
Name: lightning-Hivemind
Version: 0.1.0
Summary: Lightning strategy extension for Hivemind.
Home-page: https://github.com/Lightning-AI/lightning-Hivemind
Download-URL: https://github.com/Lightning-AI/lightning-Hivemind
Author: Lightning-AI et al.
Author-email: name@lightning.ai
License: Apache-2.0
Project-URL: Bug Tracker, https://github.com/Lightning-AI/lightning-Hivemind/issues
Project-URL: Documentation, https://lightning-Hivemind.rtfd.io/en/latest/
Project-URL: Source Code, https://github.com/Lightning-AI/lightning-Hivemind
Keywords: deep learning,pytorch,AI
Classifier: Environment :: Console
Classifier: Natural Language :: English
Classifier: Development Status :: 4 - Beta
Classifier: Intended Audience :: Developers
Classifier: Topic :: Scientific/Engineering :: Artificial Intelligence
Classifier: Topic :: Scientific/Engineering :: Information Analysis
Classifier: License :: OSI Approved :: Apache Software License
Classifier: Operating System :: OS Independent
Classifier: Programming Language :: Python :: 3
Classifier: Programming Language :: Python :: 3.8
Classifier: Programming Language :: Python :: 3.9
Classifier: Programming Language :: Python :: 3.10
Classifier: Programming Language :: Python :: 3.11
Requires-Python: >=3.8
License-File: LICENSE
Requires-Dist: lightning (>=2.0.0)
Requires-Dist: hivemind (<=1.1.5,>=1.1.0) ; sys_platform == "linux"
